odoo/addons/hr_employee_service/README.rst
odoo/addons/hr_employee_service/__init__.py
odoo/addons/hr_employee_service/__manifest__.py
odoo/addons/hr_employee_service/i18n/es.po
odoo/addons/hr_employee_service/i18n/fr.po
odoo/addons/hr_employee_service/i18n/hr_employee_service.pot
odoo/addons/hr_employee_service/models/__init__.py
odoo/addons/hr_employee_service/models/hr_employee.py
odoo/addons/hr_employee_service/readme/CONTRIBUTORS.rst
odoo/addons/hr_employee_service/readme/DESCRIPTION.rst
odoo/addons/hr_employee_service/static/description/icon.png
odoo/addons/hr_employee_service/static/description/index.html
odoo/addons/hr_employee_service/tests/__init__.py
odoo/addons/hr_employee_service/tests/test_hr_employee_service.py
odoo/addons/hr_employee_service/views/hr_employee.xml
odoo12_addon_hr_employee_service-12.0.1.0.1.dist-info/METADATA
odoo12_addon_hr_employee_service-12.0.1.0.1.dist-info/RECORD
odoo12_addon_hr_employee_service-12.0.1.0.1.dist-info/WHEEL
odoo12_addon_hr_employee_service-12.0.1.0.1.dist-info/top_level.txt
